skranger-0.8.0.dist-info/LICENSE.txt
skranger-0.8.0.dist-info/WHEEL
skranger-0.8.0.dist-info/METADATA
skranger-0.8.0.dist-info/RECORD
skranger/ranger.pyx
skranger/_version.py
skranger/ranger.cpython-39-i386-linux-gnu.so
skranger/base.py
skranger/__init__.py
skranger/ranger_.pxd
skranger/DataNumpy.h
skranger/utils/shap.py
skranger/utils/__init__.py
skranger/tree/regressor.py
skranger/tree/classifier.py
skranger/tree/survival.py
skranger/tree/_tree.py
skranger/tree/base.py
skranger/tree/__init__.py
skranger/ranger/CMakeLists.txt
skranger/ranger/COPYING
skranger/ranger/.project
skranger/ranger/.cproject
skranger/ranger/.gitignore
skranger/ranger/test/CMakeLists.txt
skranger/ranger/test/testthat.R
skranger/ranger/test/utility_test.cpp
skranger/ranger/test/test_all.cpp
skranger/ranger/test/.gitignore
skranger/ranger/test/README.md
skranger/ranger/test/testthat/test_regression.R
skranger/ranger/test/testthat/test_probability.R
skranger/ranger/test/testthat/test_survival.R
skranger/ranger/test/testthat/test_arguments.R
skranger/ranger/test/testthat/.gitignore
skranger/ranger/test/testthat/test_classification.R
skranger/ranger/cross_compile/toolchain_win64.cmake
skranger/ranger/cross_compile/toolchain_win32.cmake
skranger/ranger/cross_compile/build_all
skranger/ranger/src/globals.h
skranger/ranger/src/.gitignore
skranger/ranger/src/version.h
skranger/ranger/src/main.cpp
skranger/ranger/src/Forest/ForestClassification.cpp
skranger/ranger/src/Forest/ForestClassification.h
skranger/ranger/src/Forest/Forest.h
skranger/ranger/src/Forest/ForestProbability.h
skranger/ranger/src/Forest/Forest.cpp
skranger/ranger/src/Forest/ForestRegression.cpp
skranger/ranger/src/Forest/ForestProbability.cpp
skranger/ranger/src/Forest/ForestSurvival.cpp
skranger/ranger/src/Forest/ForestRegression.h
skranger/ranger/src/Forest/.gitignore
skranger/ranger/src/Forest/ForestSurvival.h
skranger/ranger/src/Tree/TreeRegression.h
skranger/ranger/src/Tree/Tree.cpp
skranger/ranger/src/Tree/Tree.h
skranger/ranger/src/Tree/TreeSurvival.h
skranger/ranger/src/Tree/TreeRegression.cpp
