Metadata-Version: 2.1
Name: skranger
Version: 0.8.0
Summary: Python bindings for C++ ranger random forests
Home-page: https://github.com/crflynn/skranger
License: GPL-3.0-or-later
Keywords: random,forest,ranger,machine,learning
Author: Flynn
Author-email: crf204@gmail.com
Requires-Python: >=3.8.0,<4.0.0
Classifier: Development Status :: 4 - Beta
Classifier: Intended Audience :: Science/Research
Classifier: License :: OSI Approved :: GNU General Public License v3 (GPLv3)
Classifier: License :: OSI Approved :: GNU General Public License v3 or later (GPLv3+)
Classifier: Programming Language :: C++
Classifier: Programming Language :: Python
Classifier: Programming Language :: Python :: 3
Classifier: Programming Language :: Python :: 3.10
Classifier: Programming Language :: Python :: 3.8
Classifier: Programming Language :: Python :: 3.9
Classifier: Topic :: Scientific/Engineering
Requires-Dist: scikit-learn (>=1.0)
Project-URL: Documentation, https://github.com/crflynn/skranger
Project-URL: Repository, https://github.com/crflynn/skranger
